mxbt/__init__.py
mxbt/auth.py
mxbt/bot.py
mxbt/callbacks.py
mxbt/config.py
mxbt/context.py
mxbt/filters.py
mxbt/listener.py
mxbt/match.py
mxbt/module.py
mxbt/utils.py
mxbt/webhook.py
mxbt/types/__init__.py
mxbt/types/command.py
mxbt/types/emotes.py
mxbt/types/file.py
mxbt/types/mediainfo.py
mxbt/types/msgtype.py
mxbt-0.3.7.dist-info/LICENSE
mxbt-0.3.7.dist-info/METADATA
mxbt-0.3.7.dist-info/WHEEL
mxbt-0.3.7.dist-info/top_level.txt
mxbt-0.3.7.dist-info/RECORD
