Metadata-Version: 2.1
Name: mxbt
Version: 0.3.7
Summary: Yet another Matrix bot library.
Home-page: https://codeberg.org/librehub/mxbt
Author: loliconshik3
Author-email: loliconshik3@gmail.com
Keywords: python,matrix-nio,matrix,bot,api
Classifier: Development Status :: 1 - Planning
Classifier: Intended Audience :: Developers
Classifier: Programming Language :: Python :: 3
Classifier: Operating System :: Unix
Classifier: Operating System :: MacOS :: MacOS X
Classifier: Operating System :: Microsoft :: Windows
License-File: LICENSE
Requires-Dist: matrix-nio
Requires-Dist: pillow
Requires-Dist: markdown
Requires-Dist: cryptography
Requires-Dist: filetype
Requires-Dist: aiofiles
Requires-Dist: python-dotenv
